AUTHORS.rst
CONTRIBUTING.rst
HISTORY.rst
LICENSE
MANIFEST.in
README.rst
setup.cfg
setup.py
docs/Makefile
docs/authors.rst
docs/conf.py
docs/contributing.rst
docs/history.rst
docs/index.rst
docs/installation.rst
docs/make.bat
docs/modules.rst
docs/readme.rst
docs/usage.rst
docs/_build/html/_static/ajax-loader.gif
docs/_build/html/_static/comment-bright.png
docs/_build/html/_static/comment-close.png
docs/_build/html/_static/comment.png
docs/_build/html/_static/down-pressed.png
docs/_build/html/_static/down.png
docs/_build/html/_static/file.png
docs/_build/html/_static/minus.png
docs/_build/html/_static/plus.png
docs/_build/html/_static/up-pressed.png
docs/_build/html/_static/up.png
koodous/__init__.py
koodous/api.py
koodous/cli.py
koodous/constants.py
koodous/exceptions.py
koodous/feed.py
koodous/utils.py
koodous.egg-info/PKG-INFO
koodous.egg-info/SOURCES.txt
koodous.egg-info/dependency_links.txt
koodous.egg-info/entry_points.txt
koodous.egg-info/not-zip-safe
koodous.egg-info/requires.txt
koodous.egg-info/top_level.txt
koodous/representations/__init__.py
koodous/representations/analysis.py
koodous/representations/apk.py
koodous/representations/base.py
koodous/representations/comment.py
koodous/representations/rule.py
koodous/representations/ruleset.py
tests/__init__.py
tests/test_koodous.py