Metadata-Version: 2.1
Name: koodous
Version: 2.1.1
Summary: This is the Python SDK developed by our team to use Koodous easily.
Home-page: https://github.com/koodous/python-sdk
Author: Rubén García Rojas
Author-email: rgarcia@hispasec.com
License: Apache Software License 2.0
Keywords: koodous
Platform: UNKNOWN
Classifier: Development Status :: 2 - Pre-Alpha
Classifier: Intended Audience :: Developers
Classifier: License :: OSI Approved :: Apache Software License
Classifier: Natural Language :: English
Classifier: Programming Language :: Python :: 3
Classifier: Programming Language :: Python :: 3.6
Classifier: Programming Language :: Python :: 3.7
Classifier: Programming Language :: Python :: 3.8
Requires-Python: >=3.6
License-File: LICENSE
License-File: AUTHORS.rst
